[
  {
    "id": "86cxatjka",
    "custom_id": null,
    "custom_item_id": 0,
    "name": "Design product listing page wireframe",
    "text_content": "",
    "description": "",
    "status": {
      "status": "draft",
      "id": "p90162419196_LGv9kuC6",
      "color": "#87909e",
      "type": "open",
      "orderindex": 0
    },
    "orderindex": "39908182.00000000000000000000000000000000",
    "date_created": "1734066414888",
    "date_updated": "1734067771694",
    "date_closed": null,
    "date_done": null,
    "archived": false,
    "creator": {
      "id": 55443141,
      "username": "Ray Chopra",
      "color": "",
      "email": "rp240267@gmail.com",
      "profilePicture": null
    },
    "assignees": [
      {
        "id": 55443141,
        "username": "Ray Chopra",
        "color": "",
        "initials": "RC",
        "email": "rp240267@gmail.com",
        "profilePicture": null
      }
    ],
    "group_assignees": [],
    "watchers": [
      {
        "id": 55443141,
        "username": "Ray Chopra",
        "color": "",
        "initials": "RC",
        "email": "rp240267@gmail.com",
        "profilePicture": null
      }
    ],
    "checklists": [],
    "tags": [],
    "parent": null,
    "top_level_parent": null,
    "priority": null,
    "due_date": "1734042600000",
    "start_date": null,
    "points": null,
    "time_estimate": null,
    "custom_fields": [],
    "dependencies": [],
    "linked_tasks": [],
    "locations": [],
    "team_id": "9016442698",
    "url": "https://app.clickup.com/t/86cxatjka",
    "sharing": {
      "public": false,
      "public_share_expires_on": null,
      "public_fields": [
        "assignees",
        "priority",
        "due_date",
        "content",
        "comments",
        "attachments",
        "customFields",
        "subtasks",
        "tags",
        "checklists",
        "coverimage"
      ],
      "token": null,
      "seo_optimized": false
    },
    "permission_level": "create",
    "list": {
      "id": "901605292756",
      "name": "Wireframes",
      "access": true
    },
    "project": {
      "id": "90163278106",
      "name": "Design for E-commerce platform",
      "hidden": false,
      "access": true
    },
    "folder": {
      "id": "90163278106",
      "name": "Design for E-commerce platform",
      "hidden": false,
      "access": true
    },
    "space": {
      "id": "90162419196"
    }
  },
  {
    "id": "86cxatjjc",
    "custom_id": null,
    "custom_item_id": 0,
    "name": "Create homepage wireframe",
    "text_content": "",
    "description": "",
    "status": {
      "status": "draft",
      "id": "p90162419196_LGv9kuC6",
      "color": "#87909e",
      "type": "open",
      "orderindex": 0
    },
    "orderindex": "39908181.00000000000000000000000000000000",
    "date_created": "1734066406682",
    "date_updated": "1734067768577",
    "date_closed": null,
    "date_done": null,
    "archived": false,
    "creator": {
      "id": 55443141,
      "username": "Ray Chopra",
      "color": "",
      "email": "rp240267@gmail.com",
      "profilePicture": null
    },
    "assignees": [
      {
        "id": 55443141,
        "username": "Ray Chopra",
        "color": "",
        "initials": "RC",
        "email": "rp240267@gmail.com",
        "profilePicture": null
      }
    ],
    "group_assignees": [],
    "watchers": [
      {
        "id": 55443141,
        "username": "Ray Chopra",
        "color": "",
        "initials": "RC",
        "email": "rp240267@gmail.com",
        "profilePicture": null
      }
    ],
    "checklists": [],
    "tags": [],
    "parent": null,
    "top_level_parent": null,
    "priority": null,
    "due_date": "1734129000000",
    "start_date": null,
    "points": null,
    "time_estimate": null,
    "custom_fields": [],
    "dependencies": [],
    "linked_tasks": [],
    "locations": [],
    "team_id": "9016442698",
    "url": "https://app.clickup.com/t/86cxatjjc",
    "sharing": {
      "public": false,
      "public_share_expires_on": null,
      "public_fields": [
        "assignees",
        "priority",
        "due_date",
        "content",
        "comments",
        "attachments",
        "customFields",
        "subtasks",
        "tags",
        "checklists",
        "coverimage"
      ],
      "token": null,
      "seo_optimized": false
    },
    "permission_level": "create",
    "list": {
      "id": "901605292756",
      "name": "Wireframes",
      "access": true
    },
    "project": {
      "id": "90163278106",
      "name": "Design for E-commerce platform",
      "hidden": false,
      "access": true
    },
    "folder": {
      "id": "90163278106",
      "name": "Design for E-commerce platform",
      "hidden": false,
      "access": true
    },
    "space": {
      "id": "90162419196"
    }
  },
  {
    "id": "86cxatjuu",
    "custom_id": null,
    "custom_item_id": 0,
    "name": "Build homepage prototype with navigation",
    "text_content": "",
    "description": "",
    "status": {
      "status": "draft",
      "id": "p90162419196_LGv9kuC6",
      "color": "#87909e",
      "type": "open",
      "orderindex": 0
    },
    "orderindex": "39908184.00000000000000000000000000000000",
    "date_created": "1734066458738",
    "date_updated": "1734067788208",
    "date_closed": null,
    "date_done": null,
    "archived": false,
    "creator": {
      "id": 55443141,
      "username": "Ray Chopra",
      "color": "",
      "email": "rp240267@gmail.com",
      "profilePicture": null
    },
    "assignees": [
      {
        "id": 55443141,
        "username": "Ray Chopra",
        "color": "",
        "initials": "RC",
        "email": "rp240267@gmail.com",
        "profilePicture": null
      }
    ],
    "group_assignees": [],
    "watchers": [
      {
        "id": 55443141,
        "username": "Ray Chopra",
        "color": "",
        "initials": "RC",
        "email": "rp240267@gmail.com",
        "profilePicture": null
      }
    ],
    "checklists": [],
    "tags": [],
    "parent": null,
    "top_level_parent": null,
    "priority": null,
    "due_date": "1734042600000",
    "start_date": null,
    "points": null,
    "time_estimate": null,
    "custom_fields": [],
    "dependencies": [],
    "linked_tasks": [],
    "locations": [],
    "team_id": "9016442698",
    "url": "https://app.clickup.com/t/86cxatjuu",
    "sharing": {
      "public": false,
      "public_share_expires_on": null,
      "public_fields": [
        "assignees",
        "priority",
        "due_date",
        "content",
        "comments",
        "attachments",
        "customFields",
        "subtasks",
        "tags",
        "checklists",
        "coverimage"
      ],
      "token": null,
      "seo_optimized": false
    },
    "permission_level": "create",
    "list": {
      "id": "901605292769",
      "name": "Prototypes",
      "access": true
    },
    "project": {
      "id": "90163278106",
      "name": "Design for E-commerce platform",
      "hidden": false,
      "access": true
    },
    "folder": {
      "id": "90163278106",
      "name": "Design for E-commerce platform",
      "hidden": false,
      "access": true
    },
    "space": {
      "id": "90162419196"
    }
  },
  {
    "id": "86cxaumrg",
    "custom_id": null,
    "custom_item_id": 0,
    "name": "Code Review Food Delivery GPS Location",
    "text_content": "",
    "description": "",
    "status": {
      "status": "backlog",
      "id": "p90162419191_363b0Z6E",
      "color": "#87909e",
      "type": "open",
      "orderindex": 0
    },
    "orderindex": "39908241.00000000000000000000000000000000",
    "date_created": "1734070602739",
    "date_updated": "1734071693177",
    "date_closed": null,
    "date_done": null,
    "archived": false,
    "creator": {
      "id": 55443141,
      "username": "Ray Chopra",
      "color": "",
      "email": "rp240267@gmail.com",
      "profilePicture": null
    },
    "assignees": [
      {
        "id": 55443141,
        "username": "Ray Chopra",
        "color": "",
        "initials": "RC",
        "email": "rp240267@gmail.com",
        "profilePicture": null
      }
    ],
    "group_assignees": [],
    "watchers": [
      {
        "id": 55443141,
        "username": "Ray Chopra",
        "color": "",
        "initials": "RC",
        "email": "rp240267@gmail.com",
        "profilePicture": null
      }
    ],
    "checklists": [],
    "tags": [],
    "parent": null,
    "top_level_parent": null,
    "priority": null,
    "due_date": "1734042600000",
    "start_date": null,
    "points": null,
    "time_estimate": null,
    "custom_fields": [],
    "dependencies": [],
    "linked_tasks": [],
    "locations": [],
    "team_id": "9016442698",
    "url": "https://app.clickup.com/t/86cxaumrg",
    "sharing": {
      "public": false,
      "public_share_expires_on": null,
      "public_fields": [
        "assignees",
        "priority",
        "due_date",
        "content",
        "comments",
        "attachments",
        "customFields",
        "subtasks",
        "tags",
        "checklists",
        "coverimage"
      ],
      "token": null,
      "seo_optimized": false
    },
    "permission_level": "create",
    "list": {
      "id": "901605293633",
      "name": "Code Reviews",
      "access": true
    },
    "project": {
      "id": "90163278788",
      "name": "hidden",
      "hidden": true,
      "access": true
    },
    "folder": {
      "id": "90163278788",
      "name": "hidden",
      "hidden": true,
      "access": true
    },
    "space": {
      "id": "90162419191"
    }
  },
  {
    "id": "86cxaumnj",
    "custom_id": null,
    "custom_item_id": 0,
    "name": "Code Review E-Commerce Platform Cart Module",
    "text_content": "",
    "description": "",
    "status": {
      "status": "backlog",
      "id": "p90162419191_363b0Z6E",
      "color": "#87909e",
      "type": "open",
      "orderindex": 0
    },
    "orderindex": "39908240.00000000000000000000000000000000",
    "date_created": "1734070592695",
    "date_updated": "1734071690952",
    "date_closed": null,
    "date_done": null,
    "archived": false,
    "creator": {
      "id": 55443141,
      "username": "Ray Chopra",
      "color": "",
      "email": "rp240267@gmail.com",
      "profilePicture": null
    },
    "assignees": [
      {
        "id": 55443141,
        "username": "Ray Chopra",
        "color": "",
        "initials": "RC",
        "email": "rp240267@gmail.com",
        "profilePicture": null
      }
    ],
    "group_assignees": [],
    "watchers": [
      {
        "id": 55443141,
        "username": "Ray Chopra",
        "color": "",
        "initials": "RC",
        "email": "rp240267@gmail.com",
        "profilePicture": null
      }
    ],
    "checklists": [],
    "tags": [],
    "parent": null,
    "top_level_parent": null,
    "priority": null,
    "due_date": "1734042600000",
    "start_date": null,
    "points": null,
    "time_estimate": null,
    "custom_fields": [],
    "dependencies": [],
    "linked_tasks": [],
    "locations": [],
    "team_id": "9016442698",
    "url": "https://app.clickup.com/t/86cxaumnj",
    "sharing": {
      "public": false,
      "public_share_expires_on": null,
      "public_fields": [
        "assignees",
        "priority",
        "due_date",
        "content",
        "comments",
        "attachments",
        "customFields",
        "subtasks",
        "tags",
        "checklists",
        "coverimage"
      ],
      "token": null,
      "seo_optimized": false
    },
    "permission_level": "create",
    "list": {
      "id": "901605293633",
      "name": "Code Reviews",
      "access": true
    },
    "project": {
      "id": "90163278788",
      "name": "hidden",
      "hidden": true,
      "access": true
    },
    "folder": {
      "id": "90163278788",
      "name": "hidden",
      "hidden": true,
      "access": true
    },
    "space": {
      "id": "90162419191"
    }
  }
]